cas/__init__.py
cas/aws.py
cas/concurrency.py
cas/configure.py
cas/files.py
cas/messaging.py
cas/utils.py
cas/warning.py
cas/data/__init__.py
cas/data/bim.py
cas/data/model.py
acabim_common_services_cas-1.0.69.dist-info/METADATA
acabim_common_services_cas-1.0.69.dist-info/WHEEL
acabim_common_services_cas-1.0.69.dist-info/top_level.txt
acabim_common_services_cas-1.0.69.dist-info/RECORD
