Metadata-Version: 2.1
Name: acabim-common-services-cas
Version: 1.0.69
Summary: Contains the model classes and interfaces which provide the services required for ACABIM Backend Services in Python
Home-page: UNKNOWN
Author: Compliance Audit Systems
Author-email: UNKNOWN
License: UNKNOWN
Platform: UNKNOWN
